x_jinja2/__init__.py
x_jinja2/core.py
x_jinja2-0.1.1.dist-info/licenses/LICENSE
x_jinja2-0.1.1.dist-info/METADATA
x_jinja2-0.1.1.dist-info/WHEEL
x_jinja2-0.1.1.dist-info/top_level.txt
x_jinja2-0.1.1.dist-info/RECORD
