Metadata-Version: 2.4
Name: x-jinja2
Version: 0.1.1
Summary: 让jinja2自带各类好用的filter
Home-page: https://github.com/aiziyuer/x_jinja2
Author: aiziyuer
Author-email: 910217951@qq.com
License: MIT
Classifier: Programming Language :: Python :: 3
Classifier: License :: OSI Approved :: MIT License
Classifier: Operating System :: OS Independent
Requires-Python: >=3.10
License-File: LICENSE
Requires-Dist: jinja2
Requires-Dist: jinja2_ansible_filters
Requires-Dist: jsonpath-ng
Requires-Dist: json5
Dynamic: author
Dynamic: author-email
Dynamic: classifier
Dynamic: description
Dynamic: description-content-type
Dynamic: home-page
Dynamic: license
Dynamic: license-file
Dynamic: requires-dist
Dynamic: requires-python
Dynamic: summary
